MANIFEST.in
README.rst
setup.cfg
setup.py
opencensus/__init__.py
opencensus/common/__init__.py
opencensus/common/backports/__init__.py
opencensus/common/configuration/__init__.py
opencensus/common/http_handler/__init__.py
opencensus/common/monitored_resource/__init__.py
opencensus/common/monitored_resource/aws_identity_doc_utils.py
opencensus/common/monitored_resource/gcp_metadata_config.py
opencensus/common/monitored_resource/k8s_utils.py
opencensus/common/monitored_resource/monitored_resource.py
opencensus/common/resource/__init__.py
opencensus/common/schedule/__init__.py
opencensus/common/transports/__init__.py
opencensus/common/transports/async_.py
opencensus/common/transports/base.py
opencensus/common/transports/sync.py
opencensus/common/utils/__init__.py
opencensus/common/version/__init__.py
opencensus/log/__init__.py
opencensus/metrics/__init__.py
opencensus/metrics/label_key.py
opencensus/metrics/label_value.py
opencensus/metrics/transport.py
opencensus/metrics/export/__init__.py
opencensus/metrics/export/cumulative.py
opencensus/metrics/export/gauge.py
opencensus/metrics/export/metric.py
opencensus/metrics/export/metric_descriptor.py
opencensus/metrics/export/metric_producer.py
opencensus/metrics/export/point.py
opencensus/metrics/export/summary.py
opencensus/metrics/export/time_series.py
opencensus/metrics/export/value.py
opencensus/stats/__init__.py
opencensus/stats/aggregation.py
opencensus/stats/aggregation_data.py
opencensus/stats/base_exporter.py
opencensus/stats/bucket_boundaries.py
opencensus/stats/execution_context.py
opencensus/stats/measure.py
opencensus/stats/measure_to_view_map.py
opencensus/stats/measurement.py
opencensus/stats/measurement_map.py
opencensus/stats/metric_utils.py
opencensus/stats/stats.py
opencensus/stats/stats_recorder.py
opencensus/stats/view.py
opencensus/stats/view_data.py
opencensus/stats/view_manager.py
opencensus/tags/__init__.py
opencensus/tags/tag.py
opencensus/tags/tag_key.py
opencensus/tags/tag_map.py
opencensus_perpetua.egg-info/PKG-INFO
opencensus_perpetua.egg-info/SOURCES.txt
opencensus_perpetua.egg-info/dependency_links.txt
opencensus_perpetua.egg-info/namespace_packages.txt
opencensus_perpetua.egg-info/requires.txt
opencensus_perpetua.egg-info/top_level.txt